{
  "id": "page_8276351452116568310",
  "url": "https://gethelp.211info.org/agency/22360/18669/",
  "title": "BOYS & GIRLS CLUB - 211info",
  "text": "BOYS & GIRLS CLUB OF WARM SPRINGS BOYS & GIRLS CLUB Print & Share X Print & Share Print PDF Provides a positive space for youth to engage in fun and empowering programs, such as leadership and community service, after-school programs, academic enrichment, workforce training, performing and visual arts, camps, and personal health and fitness. 50 Chukar Road Warm Springs, OR 97761 Eligibility: Ages 5-18 Hours: After school: Monday-Friday 3pm-5:30pm, non-school days: 10am-5:30pm, summer hours: Monday-Friday 8am-5pm Email (541) 553-2323 Get Directions Visit Website Phone/FAX Numbers (541) 553-2323 Main phone Main phone (541) 553-2323 Email Address: [email protected] INTAKE PROCEDURE: Walk in, call, or visit website for more information FEES: Varies by service DOCUMENTS: None AREA SERVED: City of Warm Springs Services: Boys/Girls Clubs Camps Youth Enrichment Programs Other Services Offered At This Location: LEISURE ACTIVITIES/RECREATION - HEALTH AND FITNESS If you represent this agency, update your listing here . * The community resource directory information is up to date to the best of our knowledge. However, you should always call the provider to confirm this information and make an appointment. Be sure to confirm payment information with the provider, if payment is required. 211Info does not rate, recommend or endorse any agency. We simply provide information as a public service. BOYS & GIRLS CLUB OF WARM SPRINGS",
  "metadata": {
    "depth": 3,
    "kind": "discovered",
    "quality_score": 1.0,
    "strategy_generation": 10
  },
  "timestamp": "2026-05-03T23:14:00.393878+00:00"
}