{
  "id": "page_1014029127216862076",
  "url": "https://www.211info.org/agency/20272/1245/",
  "title": "RELIEF NURSERY - 211info",
  "text": "MOUNTAINSTAR RELIEF NURSERY PRINEVILLE RELIEF NURSERY Print & Share X Print & Share Print PDF Provides intensive support through individualized case management, parenting education, home visits, and group activities. Children participate in therapeutic classrooms with low adult-child ratios and families receive home visits that promote healthy parenting and child development. Preschool Promise offered at all locations except for La Pine. 430 NW 4th Street Prineville, OR 97754 Eligibility: -Services: Ages 6 weeks-3 years; children of high-risk families -Parent and children must be enrolled to receive most services -Preschool offered Fall 2026 \"High-risk\" typically means households experiencing several of the following factors: poverty, high stress, depression, history of mental illness, lack of reliable transportation, single-parent households, criminal history, adult survivors of child abuse, history of drug or alcohol use, unemployment, low self-esteem, limited education, anger issues, homelessness, or social isolation. Hours: By appointment Email (541) 416-0146 . Get Directions Visit Website Phone/FAX Numbers Main phone (541) 416-0146 Kaycee Weeks [email protected] Email Address: [email protected] INTAKE PROCEDURE: Walk in, call, or visit website for more information FEES: None DOCUMENTS: None required at intake LANGUAGES: English, Spanish, interpretation by arrangement AREA SERVED: Crook County SITE HOURS: Monday-Friday 8am-4:30pm TRAVEL/LOCATION INFORMATION: Off NW Deer Street by Erickson's Thriftway. Services: Case/Care Management * At Risk Families Child Abuse Prevention Family Support Centers/Outreach * At Risk Families Home Based Parenting Education * At Risk Families Preschools * At Risk Families If you represent this agency, update your listing here . * The community resource directory information is up to date to the best of our knowledge. However, you should always call the provider to confirm this information and make an appointment. Be sure to confirm payment information with the provider, if payment is required. 211Info does not rate, recommend or endorse any agency. We simply provide information as a public service. MOUNTAINSTAR RELIEF NURSERY PRINEVILLE",
  "metadata": {
    "depth": 3,
    "kind": "discovered",
    "quality_score": 1.0,
    "strategy_generation": 10
  },
  "timestamp": "2026-05-03T17:40:33.586941+00:00"
}