{
  "id": "page_7336615364558479867",
  "url": "https://www.211info.org/2022/02/oregon-legislature-considering-funding-for-211info-statewide-emergency-hotline/",
  "title": "Oregon legislature considering funding for 211info, statewide emergency hotline - 211info",
  "text": "SALEM, Ore. – The sheer number of emergencies over the past three years is prompting the state to take a more formal look at 211info , an emergency hotline that’s stepped in to help answer questions for the public during the pandemic, recent extreme weather, and wildfires. Full story on KDRV . Search Popular Posts Categories Equity News",
  "metadata": {
    "depth": 3,
    "kind": "discovered",
    "quality_score": 1.0,
    "strategy_generation": 10
  },
  "timestamp": "2026-05-03T21:37:12.259746+00:00"
}