{
  "id": "page_4916742598183566913",
  "url": "https://www.211info.org/give-help/donate/donate-to-211info/",
  "title": "Donate to 211info - 211info",
  "text": "\" * \" indicates required fields Δ Company This field is for validation purposes and should be left unchanged. Choose Your Donation Amount $10 $25 $50 $100 $250 Other Amount First Name * Last Name * Email Address * Phone Number Organization Name In Honor/Memory Of Message Address * Street Address City Alabama Alaska American Samoa Arizona Arkansas California Colorado Connecticut Delaware District of Columbia Florida Georgia Guam Hawaii Idaho Illinois Indiana Iowa Kansas Kentucky Louisiana Maine Maryland Massachusetts Michigan Minnesota Mississippi Missouri Montana Nebraska Nevada New Hampshire New Jersey New Mexico New York North Carolina North Dakota Northern Mariana Islands Ohio Oklahoma Oregon Pennsylvania Puerto Rico Rhode Island South Carolina South Dakota Tennessee Texas Utah U.S. Virgin Islands Vermont Virginia Washington West Virginia Wisconsin Wyoming Armed Forces Americas Armed Forces Europe Armed Forces Pacific State ZIP Code Total Credit Card * Card Details Cardholder Name CAPTCHA All Transations are 100% SSL secure and encrypted. We never store your credit card information. Payments are processed through Stripe. By clicking Submit Donation, you agree to our terms and conditions & privacy policy.",
  "metadata": {
    "depth": 2,
    "kind": "discovered",
    "quality_score": 1.0,
    "strategy_generation": 0
  },
  "timestamp": "2026-05-02T23:40:05.434465+00:00"
}