{
  "id": "page_8008940424267800870",
  "url": "https://www.211info.org/agency/4768/3534/",
  "title": "HEALTH SERVICES - 211info",
  "text": "PARKINSON'S RESOURCES OF OREGON HEALTH SERVICES Print & Share X Print & Share Print PDF Provides support and services for patients and families living with a diagnosis of Parkinson's disease. Services include support groups, exercise and speech classes, education workshops, case management, and counseling. Offers hybrid formats, online, in-person groups, and outdoor activities. 8880 SW Nimbus Avenue Suite B Beaverton, OR 97008 Eligibility: Individuals with Parkinson's Disease and their caregivers and friends Hours: Monday-Friday 9am-5pm Email (503) 594-0901 Get Directions Visit Website Phone/FAX Numbers Helpline (503) 594-0901 Helpline (800) 426-6806 Toll-free Email Address: [email protected] INTAKE PROCEDURE: Call or visit website for more information FEES: None DOCUMENTS: None AREA SERVED: State of Oregon Services: Case/Care Management * Parkinson's Disease Health/Disability Related Counseling * Parkinson's Disease Health/Disability Related Support Groups * Parkinson's Disease Therapeutic Exercise * Parkinson's Disease If you represent this agency, update your listing here . * The community resource directory information is up to date to the best of our knowledge. However, you should always call the provider to confirm this information and make an appointment. Be sure to confirm payment information with the provider, if payment is required. 211Info does not rate, recommend or endorse any agency. We simply provide information as a public service. PARKINSON'S RESOURCES OF OREGON",
  "metadata": {
    "depth": 3,
    "kind": "discovered",
    "quality_score": 1.0,
    "strategy_generation": 10
  },
  "timestamp": "2026-05-03T18:04:35.284891+00:00"
}