{
  "id": "page_7041630528894701562",
  "url": "https://www.211info.org/agency/4064/14492/",
  "title": "MINORITY AIDS INITIATIVE - 211info",
  "text": "OHSU PARTNERSHIP PROJECT MINORITY AIDS INITIATIVE Print & Share X Print & Share Print PDF Helps individuals obtain insurance, access medical and mental health care, substance abuse services, housing, and other services. Offers intensive and culturally appropriate services. 2525 SW 1st Avenue Suite 1201 Portland, OR 97202 Eligibility: Refugees and immigrants living with HIV/AIDS Hours: Monday-Friday 9am-5pm Email (503) 731-9593 Get Directions Visit Website Phone/FAX Numbers Main phone (503) 731-9593 David Ochan & Frank Mollel Email Address: [email protected] INTAKE PROCEDURE: Call for information FEES: None DOCUMENTS: Documentation of HIV status LANGUAGES: English, Swahili, Lusage, Acholi, Luganda, interpretation by arrangement AREA SERVED: Clackamas, Columbia, Multnomah, Washington, and Yamhill Counties TRAVEL/LOCATION INFORMATION: TriMet bus lines 9, 12, 35, and 40 Services: Case/Care Management * AIDS/HIV Issues Navigator Programs * AIDS/HIV Issues Other Services Offered At This Location: INDIVIDUAL AND FAMILY SUPPORT SERVICES - PARTNERSHIP PROJECT SPECIALIZED TREATMENT AND PREVENTION - TRANSGENDER HEALTH PROGRAM If you represent this agency, update your listing here . * The community resource directory information is up to date to the best of our knowledge. However, you should always call the provider to confirm this information and make an appointment. Be sure to confirm payment information with the provider, if payment is required. 211Info does not rate, recommend or endorse any agency. We simply provide information as a public service. OHSU PARTNERSHIP PROJECT",
  "metadata": {
    "depth": 3,
    "kind": "discovered",
    "quality_score": 1.0,
    "strategy_generation": 10
  },
  "timestamp": "2026-05-03T15:26:40.174557+00:00"
}