{
  "id": "page_6871811909743515994",
  "url": "https://gethelp.211info.org/get-help/volunteering-donating/volunteer-opportunities-veterans/",
  "title": "Volunteer Opportunities * Veterans - 211info",
  "text": "- Radius - 5 Miles 10 Miles 25 Miles 50 Miles 100 Miles Search by Provider Name > New Search > Volunteering & Donating > Volunteer Opportunities * Veterans 1 Matching Service Providers Refine Results - Select - No Filter Autism Spectrum Disorder Child Abuse Issues Disaster/Emergency Issues Domestic Violence Issues Foster Children Homelessness Issues Seasonal Workers Veterans Print & Share All Results X Print & Share Print PDF DISABLED AMERICAN VETERANS VA REGIONAL OFFICE OREGON DAV TRANSPORTATION NETWORK PORTLAND VA MEDICAL CENTER Print & Share X Print & Share Print PDF Offers transportation to and from the Portland VA Medical Center. Does not provide wheelchair-accessible transportation or door-to-door service. 100 SW Main Street Room 212a Portland, OR 97204 Eligibility: Veterans who have a verifiable appointment at Portland VA Medical Center. Hours: Varies (503) 721-7804 Get Directions Visit Website More Details DISABLED AMERICAN VETERANS VA REGIONAL OFFICE OREGON DAV TRANSPORTATION NETWORK PORTLAND VA MEDICAL CENTER",
  "metadata": {
    "depth": 2,
    "kind": "discovered",
    "quality_score": 1.0,
    "strategy_generation": 4
  },
  "timestamp": "2026-05-03T02:27:53.673827+00:00"
}