{
  "id": "page_1888313799329138409",
  "url": "https://www.211info.org/agency/23667/24163/",
  "title": "PRIMARY AND BEHAVIORAL HEALTH - 211info",
  "text": "WARRENTON MEDICAL GROUP PRIMARY AND BEHAVIORAL HEALTH Print & Share X Print & Share Print PDF Provides primary care and behavioral health care services. 1639 SE Ensign Lane Suite B103 Warrenton, OR 97146 Eligibility: Unrestricted Hours: Monday-Friday 7am-7pm (503) 338-4500 Get Directions Visit Website Phone/FAX Numbers Main phone (503) 338-4500 INTAKE PROCEDURE: Call to schedule an appointment FEES: Accepts Medicaid, Medicare, and private insurance. Discounts, financial assistance, and payment plans may be available for uninsured patients. DOCUMENTS: Insurance information, if applicable AREA SERVED: Clatsop County TRAVEL/LOCATION INFORMATION: Located in Warrenton Highlands business park Services: Community Clinics Community Mental Health Agencies General Medical Care Other Services Offered At This Location: OUTPATIENT HEALTH FACILITIES - COLUMBIA MEMORIAL URGENT CARE If you represent this agency, update your listing here . * The community resource directory information is up to date to the best of our knowledge. However, you should always call the provider to confirm this information and make an appointment. Be sure to confirm payment information with the provider, if payment is required. 211Info does not rate, recommend or endorse any agency. We simply provide information as a public service. WARRENTON MEDICAL GROUP",
  "metadata": {
    "depth": 3,
    "kind": "discovered",
    "quality_score": 1.0,
    "strategy_generation": 10
  },
  "timestamp": "2026-05-03T13:41:14.530169+00:00"
}