{
  "id": "page_8241901244271498438",
  "url": "https://gethelp.211info.org/agency/2013/17743/",
  "title": "211INFO RESOURCE PARENT SUPPORT - 211info",
  "text": "211INFO 211INFO RESOURCE PARENT SUPPORT Print & Share X Print & Share Print PDF Offers support, resource referral, and additional after-hours support for foster parents. Eligibility: Any foster parent with an ODHS Child Welfare case or in the Oregon Foster Care System Hours: 24 hours per day / 7 days per week Email 211 Visit Website Phone/FAX Numbers 211 211info (503) 222-5555 Alternate (503) 226-3099 Administrative Line 898211 Text Short Code Select \"Foster Parent\" Option 211 Email Address: [email protected] INTAKE PROCEDURE: Call for information. Voicemail option if specialist is unavailable. FEES: None LANGUAGES: English, interpretation or signing by arrangement AREA SERVED: State of Oregon Services: Adolescent/Youth Counseling * Adoption/Foster Care/Kinship Care Issues Adoption and Foster/Kinship Care Support Groups Benefits and Services Assistance * Adoption/Foster Care/Kinship Care Issues Case/Care Management * Adoption/Foster Care/Kinship Care Issues Child Abuse Support Groups * Foster Children Child Guidance * Adoption/Foster Care/Kinship Care Issues Child Welfare/Family Services Associations Children's Clothing * Foster Children Community Calendars * Adoption/Foster Care/Kinship Care Issues Family Preservation Programs Foster Home Placement Foster Parent/Family Recruitment General Crisis Intervention Hotlines * Adoption/Foster Care/Kinship Care Issues Government Complaints/Government Ombudsman Offices * Adoption/Foster Care/Kinship Care Issues Housing Related Coordinated Entry * Adoption/Foster Care/Kinship Care Issues Mental Health Evaluation * Adoption/Foster Care/Kinship Care Issues Parent/Child Activity Groups * Adoption/Foster Care/Kinship Care Issues Parenting Helplines * Foster Parents Placements for Children and Youth Specialized Information and Referral * Adoption/Foster Care/Kinship Care Issues Talklines/Warmlines * Adoption/Foster Care/Kinship Care Issues Tutoring Services * Adoption/Foster Care/Kinship Care Issues Workshops/Symposiums * Adoption/Foster Care/Kinship Care Issues Other Services Offered At This Location: DISASTER SERVICES - 211INFO DCM LINE DISASTER SERVICES - GORGE CITIZEN ALERT PROGRAM DISASTER SERVICES - SEVERE WINTER WEATHER INFORMATION SERVICES DISASTER SERVICES - WINTER AND SEVERE WEATHER INFORMATION SERVICES MULTNOMAH COUNTY FOOD - 211INFO SNAP AND FOOD ACCESS HOUSING/SHELTER - COORDINATED ENTRY FOR FAMILIES MULTNOMAH COUNTY HOUSING/SHELTER - MULTNOMAH COUNTY EVICTION PREVENTION PROGRAM HOUSING/SHELTER - MULTNOMAH COUNTY FAMILY SHELTER WAITLIST INDIVIDUAL AND FAMILY SUPPORT SERVICES - 211INFO CHILD CARE INDIVIDUAL AND FAMILY SUPPORT SERVICES - 211INFO COORDINATION CENTER INDIVIDUAL AND FAMILY SUPPORT SERVICES - 211INFO MATERNAL AND CHILD HEALTH PROGRAM INFORMATION SERVICES - 211INFO ICE IMPACT SUPPORT INFORMATION SERVICES - 211INFO INFORMATION AND REFERRAL INFORMATION SERVICES - 211INFO OUTREACH AND MATERIALS REQUESTS INFORMATION SERVICES - 211INFO RESOURCE DEPARTMENT INFORMATION SERVICES - OREGON HIV/STD HOTLINE MONEY MANAGEMENT - 211INFO FINANCIAL WELLNESS UTILITIES - 211INFO UTILITY ASSISTANCE UPDATES If you represent this agency, update your listing here . * The community resource directory information is up to date to the best of our knowledge. However, you should always call the provider to confirm this information and make an appointment. Be sure to confirm payment information with the provider, if payment is required. 211Info does not rate, recommend or endorse any agency. We simply provide information as a public service. No Mapping Information Available",
  "metadata": {
    "depth": 3,
    "kind": "discovered",
    "quality_score": 1.0,
    "strategy_generation": 10
  },
  "timestamp": "2026-05-03T21:59:50.154688+00:00"
}