{
  "id": "page_1518313178667926418",
  "url": "https://www.211info.org/agency/4124/3111/",
  "title": "OREGON STATE HOSPITAL - 211info",
  "text": "OREGON STATE HOSPITAL SALEM OREGON STATE HOSPITAL Print & Share X Print & Share Print PDF State-administered psychiatric facility provides inpatient psychiatric care. 2600 Center Street NE Salem, OR 97301 Eligibility: Age 18 and older who need intensive psychiatric treatment for severe and persistent mental illness. Serves patients in the following commitment categories: Civil: People who have been found by the courts to be an imminent danger to themselves or others, or who are unable to provide for their own basic health and safety needs due to their mental illness. Includes both involuntary commitment and voluntary commitment by guardian. Also applies to people who require hospital-level neuropsychiatric care for dementia, organic brain injury, or other mental illness, often with co-occurring significant medical issues. Guilty Except for Insanity (GEI): People who committed a crime related to their mental illness. Depending on the nature of their crime, patients are under the jurisdiction of either the Psychiatric Security Review Board for more severe crimes or the Oregon State Hospital Review Panel for lesser crimes. Aid and Assist: People who have been arrested but are not able to participate in their trial because of a mental illness. Courts issue an order to send defendants to the Oregon State Hospital for stabilization and mental health treatment that enables them to understand the criminal charges against them and \"aid and assist\" in their own defense. Hours: 24 hours per day / 7 days per week (503) 945-2800 Get Directions Visit Website Phone/FAX Numbers Main phone (503) 945-2800 Toll-free (800) 544-7078 Salem Reception INTAKE PROCEDURE: Must be referred by a community mental health center, court system, or legal guardian. FEES: Varies by service DOCUMENTS: None required at intake LANGUAGES: English, interpretation by arrangement AREA SERVED: State of Oregon Services: Inpatient Mental Health Facilities If you represent this agency, update your listing here . * The community resource directory information is up to date to the best of our knowledge. However, you should always call the provider to confirm this information and make an appointment. Be sure to confirm payment information with the provider, if payment is required. 211Info does not rate, recommend or endorse any agency. We simply provide information as a public service. OREGON STATE HOSPITAL SALEM",
  "metadata": {
    "depth": 3,
    "kind": "discovered",
    "quality_score": 1.0,
    "strategy_generation": 10
  },
  "timestamp": "2026-05-03T13:28:58.725391+00:00"
}